{
  "data": {
    "id": 111825,
    "attributes": {
      "title": "CAMILA COELHO (@camilacoelho) • Instagram photos and videos",
      "description": "Share LOVE wherever you go!\nFounder @elaluz & @camilacoelhocollection\n@epilepsyfdn Ambassador & Board Member💜",
      "metaData": {
        "url": "https://www.instagram.com/camilacoelho/",
        "icon": "",
        "type": "Profile",
        "title": "CAMILA COELHO (@camilacoelho) • Instagram photos and videos",
        "covers": [
          "https://scontent.cdninstagram.com/v/t51.2885-19/402327079_3692889090991256_4723081888164946863_n.jpg?stp=dst-jpg_s100x100&_nc_cat=1&ccb=1-7&_nc_sid=3fd06f&_nc_ohc=aXU4plFpicoAX-OBd5l&_nc_oc=AQmEj9FNCQypOqtc8U_U41ZAQu2nOvnolhK8zubRrdNWShm42oTUvlbboxHjNEQm5FqdLDF0ZZroFucixzeiYgmW&_nc_ht=scontent.cdninstagram.com&oh=00_AfCrSA85wLCMnDOiYJ2fgPUKJg2d1uMu75v6sBkzdTUXyA&oe=65BCE630"
        ],
        "defaultIcon": ""
      },
      "upvotes": 0,
      "downvotes": null,
      "is_favourite": false,
      "media": {
        "covers": [
          "https://scontent.cdninstagram.com/v/t51.2885-19/402327079_3692889090991256_4723081888164946863_n.jpg?stp=dst-jpg_s100x100&_nc_cat=1&ccb=1-7&_nc_sid=3fd06f&_nc_ohc=aXU4plFpicoAX-OBd5l&_nc_oc=AQmEj9FNCQypOqtc8U_U41ZAQu2nOvnolhK8zubRrdNWShm42oTUvlbboxHjNEQm5FqdLDF0ZZroFucixzeiYgmW&_nc_ht=scontent.cdninstagram.com&oh=00_AfCrSA85wLCMnDOiYJ2fgPUKJg2d1uMu75v6sBkzdTUXyA&oe=65BCE630"
        ]
      },
      "media_type": "Profile",
      "url": "https://www.instagram.com/camilacoelho/",
      "text": null,
      "remarks": "",
      "Comments": null,
      "Shares": null,
      "post_type": "SavedToCurateit",
      "broken_link": false,
      "status_code": "200",
      "highlightId": null,
      "socialfeed_obj": {
        "id": "camila-coelho-(@camilacoelho)-•-instagram-photos-and-videos",
        "posts": "12,178",
        "title": "CAMILA COELHO (@camilacoelho) • Instagram photos and videos",
        "followers": "10M",
        "connections": "959",
        "description": "Share LOVE wherever you go!\nFounder @elaluz & @camilacoelhocollection\n@epilepsyfdn Ambassador & Board Member💜",
        "profile_url": "https://www.instagram.com/camilacoelho/",
        "profile_image_url": "https://scontent.cdninstagram.com/v/t51.2885-19/402327079_3692889090991256_4723081888164946863_n.jpg?stp=dst-jpg_s100x100&_nc_cat=1&ccb=1-7&_nc_sid=3fd06f&_nc_ohc=aXU4plFpicoAX-OBd5l&_nc_oc=AQmEj9FNCQypOqtc8U_U41ZAQu2nOvnolhK8zubRrdNWShm42oTUvlbboxHjNEQm5FqdLDF0ZZroFucixzeiYgmW&_nc_ht=scontent.cdninstagram.com&oh=00_AfCrSA85wLCMnDOiYJ2fgPUKJg2d1uMu75v6sBkzdTUXyA&oe=65BCE630"
      },
      "socialfeedAt": null,
      "platform": "Instagram",
      "fileType": null,
      "html_file_link": null
    }
  },
  "meta": {}
}
